dracula/.DS_Store
dracula/__init__.py
dracula/dracula.py
dracula-0.1.3.dist-info/WHEEL
dracula-0.1.3.dist-info/METADATA
dracula-0.1.3.dist-info/RECORD
