Metadata-Version: 2.1
Name: dracula
Version: 0.1.3
Summary: Dracula colors palette, becaue why not
Author-email: "f.catus" <none@none.com>
Project-URL: Home, https://github.comm/Alyetama/dracula
